[
  {
    "outputFileName": "wwwroot/js/Beneficiary/updateUser.bundle.min.js",
    "inputFiles": [
      "wwwroot/js/Beneficiary/update-user.js"
    ],

    "minify": {
      "enabled": true,
      "renameLocals": true
    }

  },
  {
    "outputFileName": "wwwroot/js/Beneficiary/signup.bundle.min.js",
    "inputFiles": [
      "wwwroot/js/Beneficiary/signup.js"
    ],

    "minify": {
      "enabled": true,
      "renameLocals": true
    }

  },
  {
    "outputFileName": "wwwroot/js/Beneficiary/sendEmail.bundle.min.js",
    "inputFiles": [
      "wwwroot/js/Beneficiary/send-email.js"
    ],

    "minify": {
      "enabled": true,
      "renameLocals": true
    }

  },
  {
    "outputFileName": "wwwroot/js/Beneficiary/resetPassword.bundle.min.js",
    "inputFiles": [
      "wwwroot/js/Beneficiary/reset-password.js"
    ],

    "minify": {
      "enabled": true,
      "renameLocals": true
    }

  }
]
